LICENSE
MANIFEST.in
README.md
setup.py
tap_activecampaign/__init__.py
tap_activecampaign/client.py
tap_activecampaign/discover.py
tap_activecampaign/schema.py
tap_activecampaign/streams.py
tap_activecampaign/sync.py
tap_activecampaign/transform.py
tap_activecampaign.egg-info/PKG-INFO
tap_activecampaign.egg-info/SOURCES.txt
tap_activecampaign.egg-info/dependency_links.txt
tap_activecampaign.egg-info/entry_points.txt
tap_activecampaign.egg-info/requires.txt
tap_activecampaign.egg-info/top_level.txt
tap_activecampaign/schemas/account_contacts.json
tap_activecampaign/schemas/account_custom_field_values.json
tap_activecampaign/schemas/account_custom_fields.json
tap_activecampaign/schemas/accounts.json
tap_activecampaign/schemas/activities.json
tap_activecampaign/schemas/addresses.json
tap_activecampaign/schemas/automation_blocks.json
tap_activecampaign/schemas/automations.json
tap_activecampaign/schemas/bounce_logs.json
tap_activecampaign/schemas/brandings.json
tap_activecampaign/schemas/calendars.json
tap_activecampaign/schemas/campaign_links.json
tap_activecampaign/schemas/campaign_lists.json
tap_activecampaign/schemas/campaign_messages.json
tap_activecampaign/schemas/campaigns.json
tap_activecampaign/schemas/configs.json
tap_activecampaign/schemas/contact_automations.json
tap_activecampaign/schemas/contact_conversions.json
tap_activecampaign/schemas/contact_custom_field_options.json
tap_activecampaign/schemas/contact_custom_field_rels.json
tap_activecampaign/schemas/contact_custom_field_values.json
tap_activecampaign/schemas/contact_custom_fields.json
tap_activecampaign/schemas/contact_data.json
tap_activecampaign/schemas/contact_deals.json
tap_activecampaign/schemas/contact_emails.json
tap_activecampaign/schemas/contact_lists.json
tap_activecampaign/schemas/contact_tags.json
tap_activecampaign/schemas/contacts.json
tap_activecampaign/schemas/conversion_triggers.json
tap_activecampaign/schemas/conversions.json
tap_activecampaign/schemas/deal_activities.json
tap_activecampaign/schemas/deal_custom_field_values.json
tap_activecampaign/schemas/deal_custom_fields.json
tap_activecampaign/schemas/deal_group_users.json
tap_activecampaign/schemas/deal_groups.json
tap_activecampaign/schemas/deal_stages.json
