Metadata-Version: 2.1
Name: tap-activecampaign
Version: 1.3.1
Summary: Singer.io tap for extracting data from the Google Search Console API
Author: jeff.huth@bytecode.io
Classifier: Programming Language :: Python :: 3 :: Only
License-File: LICENSE
Requires-Dist: backoff==1.10.0
Requires-Dist: pyhumps==3.8.0
Requires-Dist: requests==2.32.4
Requires-Dist: singer-python==5.13.2
Provides-Extra: dev
Requires-Dist: ipdb; extra == "dev"
Provides-Extra: test
Requires-Dist: pylint; extra == "test"
Requires-Dist: nose; extra == "test"
